lambda_explorer/__init__.py
lambda_explorer/__main__.py
lambda_explorer/cli.py
lambda_explorer/logo/android-chrome-192x192.png
lambda_explorer/logo/android-chrome-512x512.png
lambda_explorer/logo/apple-touch-icon.png
lambda_explorer/logo/favicon-16x16.png
lambda_explorer/logo/favicon-32x32.png
lambda_explorer/logo/favicon.ico
lambda_explorer/tools/__init__.py
lambda_explorer/tools/aero_formulas.py
lambda_explorer/tools/aero_tools.py
lambda_explorer/tools/default_manager.py
lambda_explorer/tools/defaults.yaml
lambda_explorer/tools/formula_base.py
lambda_explorer/tools/formula_registry.py
lambda_explorer/tools/gui_tools.py
lambda_explorer/tools/interpolation_formula.py
lambda_explorer/tools/layout_manager.py
lambda_explorer/tools/solver.py
lambda_explorer/tools/window_state_manager.py
lambda_explorer-1.0.0.dist-info/METADATA
lambda_explorer-1.0.0.dist-info/WHEEL
lambda_explorer-1.0.0.dist-info/entry_points.txt
lambda_explorer-1.0.0.dist-info/top_level.txt
lambda_explorer-1.0.0.dist-info/RECORD
