Metadata-Version: 2.4
Name: lambda-explorer
Version: 1.0.0
Summary: GUI tool for exploring formulas using DearPyGui
Author: Noel Ernsting Luz
Requires-Python: >=3.8
Requires-Dist: dearpygui
Requires-Dist: sympy
Requires-Dist: coloredlogs
Requires-Dist: verboselogs
Requires-Dist: pyyaml
Requires-Dist: matplotlib
